README.md
setup.py
sretools/__init__.py
sretools/commandline.py
sretools/csvfmt.py
sretools/dbx.py
sretools/dsq.py
sretools/incident.py
sretools/jdbc_call.py
sretools/json2html.py
sretools/json2table.py
sretools/json2xml.py
sretools/json2yaml.py
sretools/jsonfmt.py
sretools/ltexpect.py
sretools/nonascii.py
sretools/t.py
sretools/tblfmt.py
sretools/xml2json.py
sretools/yaml2html.py
sretools/yaml2json.py
sretools/yssh.py
sretools.egg-info/PKG-INFO
sretools.egg-info/SOURCES.txt
sretools.egg-info/dependency_links.txt
sretools.egg-info/entry_points.txt
sretools.egg-info/requires.txt
sretools.egg-info/top_level.txt