Metadata-Version: 2.1
Name: sretools
Version: 0.1.130
Summary: SRE console/terminal toolbox
Home-page: https://github.com/laowangv5/sretools
Author: Yonghang Wang
Author-email: wyhang@gmail.com
License: MIT
Keywords: sretool,ssh,expect,json2html,xml2json,json2xml,jsonfmt,dbx,qx,jq,dsq,dsquery
Platform: UNKNOWN
Classifier: License :: OSI Approved :: MIT License
